templatrix/__init__.py
templatrix/cli.py
templatrix/src/__init__.py
templatrix/src/fastapi_template.py
templatrix/src/flask_template.py
templatrix/src/templates/template_fastapi/main.py
templatrix/src/templates/template_fastapi/databases/users.db
templatrix/src/templates/template_fastapi/db/__init__.py
templatrix/src/templates/template_fastapi/db/database.py
templatrix/src/templates/template_fastapi/db/populate.py
templatrix/src/templates/template_fastapi/models/__init__.py
templatrix/src/templates/template_fastapi/models/user.py
templatrix/src/templates/template_fastapi/routes/__init__.py
templatrix/src/templates/template_fastapi/routes/health.py
templatrix/src/templates/template_fastapi/routes/users.py
templatrix/src/templates/template_fastapi/tests/__init__.py
templatrix/src/templates/template_fastapi/tests/conftest.py
templatrix/src/templates/template_fastapi/tests/test_users.py
templatrix/src/templates/template_fastapi/utils/__init__.py
templatrix/src/templates/template_fastapi/utils/config.py
templatrix/src/templates/template_fastapi/utils/database.py
templatrix/src/templates/template_fastapi/utils/responses.py
templatrix/src/templates/template_flask/config.py
templatrix/src/templates/template_flask/run.py
templatrix/src/templates/template_flask/app/__init__.py
templatrix/src/templates/template_flask/app/database.py
templatrix/src/templates/template_flask/app/auth/__init__.py
templatrix/src/templates/template_flask/app/auth/auth.py
templatrix/src/templates/template_flask/app/databases/test_users.db
templatrix/src/templates/template_flask/app/databases/users.db
templatrix/src/templates/template_flask/app/db/__init__.py
templatrix/src/templates/template_flask/app/db/database.py
templatrix/src/templates/template_flask/app/db/populate.py
templatrix/src/templates/template_flask/app/models/__init__.py
templatrix/src/templates/template_flask/app/models/user.py
templatrix/src/templates/template_flask/app/routes/__init__.py
templatrix-0.1.1.dist-info/licenses/LICENSE
templatrix-0.1.1.dist-info/METADATA
templatrix-0.1.1.dist-info/WHEEL
templatrix-0.1.1.dist-info/entry_points.txt
templatrix-0.1.1.dist-info/top_level.txt
templatrix-0.1.1.dist-info/RECORD
