Metadata-Version: 2.4
Name: templatrix
Version: 0.1.1
Summary: Python package for quickly generating structured web application templates for FastAPI and Flask frameworks
Author-email: SaiDhinakar <saidhinakars899@gmail.com>
Requires-Python: >=3.12
License-File: LICENSE
Requires-Dist: fastapi[all,standard]>=0.115.13
Requires-Dist: flask>=3.1.1
Requires-Dist: httpx>=0.28.1
Requires-Dist: pytest>=8.4.1
Requires-Dist: python-dotenv>=1.1.0
Requires-Dist: setuptools>=80.9.0
Requires-Dist: uvicorn>=0.34.3
Requires-Dist: rich>=13.7.1
Dynamic: license-file
